lewdsfunpy/__init__.py
lewdsfunpy/lewds.py
lewdsfunpy-0.0.4.dist-info/LICENSE
lewdsfunpy-0.0.4.dist-info/METADATA
lewdsfunpy-0.0.4.dist-info/WHEEL
lewdsfunpy-0.0.4.dist-info/top_level.txt
lewdsfunpy-0.0.4.dist-info/RECORD
