Metadata-Version: 2.1
Name: lewdsfunpy
Version: 0.0.4
Summary: A small package for lewds api!
Home-page: https://github.com/MxsicXYZ/lewdsfunpy
Author: Xynnix
Author-email: admin@lewds.fun
License: UNKNOWN
Project-URL: Bug Tracker, https://github.com/MxsicXYZ/lewdsfunpy/issues
Platform: UNKNOWN
Classifier: Programming Language :: Python :: 3
Classifier: License :: OSI Approved :: MIT License
Classifier: Operating System :: OS Independent
Requires-Python: >=3.6
License-File: LICENSE
Provides-Extra: all
Requires-Dist: requests ; extra == 'all'
Requires-Dist: python-dotenv ; extra == 'all'
